pokelichis/_Init_.py
pokelichis/__init__.py
pokelichis/pokemon.csv
pokelichis/random_pokemon.py
pokelichis-1.0.1.dist-info/METADATA
pokelichis-1.0.1.dist-info/WHEEL
pokelichis-1.0.1.dist-info/top_level.txt
pokelichis-1.0.1.dist-info/RECORD
